<?xml version="1.0" encoding="utf-8"?>
<world X="2000" Y="2000">
  <player X="116" Y="90"></player>
  <obstacle X="3" Y="-2">Border</obstacle>
  <obstacle X="0" Y="211">Border</obstacle>
  <obstacle X="88" Y="-4">Border</obstacle>
  <obstacle X="2" Y="71">Border</obstacle>
  <obstacle X="3" Y="283">Border</obstacle>
  <obstacle X="2" Y="142">Border</obstacle>
  <obstacle X="-3" Y="638">Border</obstacle>
  <obstacle X="-1" Y="566">Border</obstacle>
  <obstacle X="337" Y="-5">Border</obstacle>
  <obstacle X="2" Y="356">Border</obstacle>
  <obstacle X="2" Y="425">Border</obstacle>
  <obstacle X="1" Y="496">Border</obstacle>
  <obstacle X="253" Y="-4">Border</obstacle>
  <obstacle X="171" Y="-5">Border</obstacle>
  <obstacle X="663" Y="-3">Border</obstacle>
  <obstacle X="744" Y="-3">Border</obstacle>
  <obstacle X="421" Y="-2">Border</obstacle>
  <obstacle X="501" Y="-3">Border</obstacle>
  <obstacle X="583" Y="-4">Border</obstacle>
  <obstacle X="825" Y="-5">Border</obstacle>
  <obstacle X="908" Y="-3">Border</obstacle>
  <obstacle X="993" Y="-3">Border</obstacle>
  <obstacle X="1077" Y="-4">Border</obstacle>
  <obstacle X="1159" Y="-6">Border</obstacle>
  <obstacle X="1242" Y="-8">Border</obstacle>
  <obstacle X="1326" Y="-7">Border</obstacle>
  <obstacle X="1411" Y="-7">Border</obstacle>
  <obstacle X="1497" Y="-8">Border</obstacle>
  <obstacle X="-5" Y="922">Border</obstacle>
  <obstacle X="-3" Y="708">Border</obstacle>
  <obstacle X="-3" Y="777">Border</obstacle>
  <obstacle X="-3" Y="849">Border</obstacle>
  <obstacle X="1583" Y="-5">Border</obstacle>
  <obstacle X="1667" Y="-6">Border</obstacle>
  <obstacle X="1752" Y="-5">Border</obstacle>
  <obstacle X="1913" Y="-4">Border</obstacle>
  <obstacle X="1911" Y="67">Border</obstacle>
  <obstacle X="1837" Y="-4">Border</obstacle>
  <obstacle X="1911" Y="137">Border</obstacle>
  <obstacle X="1910" Y="208">Border</obstacle>
  <obstacle X="1912" Y="347">Border</obstacle>
  <obstacle X="1911" Y="277">Border</obstacle>
  <obstacle X="1911" Y="416">Border</obstacle>
  <obstacle X="1913" Y="487">Border</obstacle>
  <obstacle X="1911" Y="558">Border</obstacle>
  <obstacle X="1910" Y="629">Border</obstacle>
  <obstacle X="1909" Y="700">Border</obstacle>
  <obstacle X="1909" Y="771">Border</obstacle>
  <obstacle X="1906" Y="841">Border</obstacle>
  <obstacle X="1907" Y="913">Border</obstacle>
  <obstacle X="1910" Y="985">Border</obstacle>
  <obstacle X="1913" Y="1057">Border</obstacle>
  <obstacle X="1915" Y="1129">Border</obstacle>
  <obstacle X="1914" Y="1199">Border</obstacle>
  <obstacle X="1911" Y="1270">Border</obstacle>
  <obstacle X="1910" Y="1342">Border</obstacle>
  <obstacle X="1909" Y="1414">Border</obstacle>
  <obstacle X="1910" Y="1484">Border</obstacle>
  <obstacle X="1910" Y="1555">Border</obstacle>
  <obstacle X="1911" Y="1627">Border</obstacle>
  <obstacle X="1911" Y="1698">Border</obstacle>
  <obstacle X="1911" Y="1770">Border</obstacle>
  <obstacle X="1911" Y="1844">Border</obstacle>
  <obstacle X="1913" Y="1917">Border</obstacle>
  <obstacle X="1828" Y="1918">Border</obstacle>
  <obstacle X="1743" Y="1919">Border</obstacle>
  <obstacle X="1661" Y="1920">Border</obstacle>
  <obstacle X="1576" Y="1922">Border</obstacle>
  <obstacle X="1492" Y="1921">Border</obstacle>
  <obstacle X="1408" Y="1921">Border</obstacle>
  <obstacle X="1324" Y="1922">Border</obstacle>
  <obstacle X="1087" Y="1924">Border</obstacle>
  <obstacle X="1245" Y="1925">Border</obstacle>
  <obstacle X="1001" Y="1924">Border</obstacle>
  <obstacle X="917" Y="1920">Border</obstacle>
  <obstacle X="836" Y="1919">Border</obstacle>
  <obstacle X="751" Y="1918">Border</obstacle>
  <obstacle X="672" Y="1923">Border</obstacle>
  <obstacle X="1169" Y="1926">Border</obstacle>
  <obstacle X="-7" Y="1065">Border</obstacle>
  <obstacle X="-5" Y="994">Border</obstacle>
  <obstacle X="-8" Y="1136">Border</obstacle>
  <obstacle X="-7" Y="1279">Border</obstacle>
  <obstacle X="-6" Y="1208">Border</obstacle>
  <obstacle X="-7" Y="1346">Border</obstacle>
  <obstacle X="-5" Y="1419">Border</obstacle>
  <obstacle X="-5" Y="1489">Border</obstacle>
  <obstacle X="-5" Y="1560">Border</obstacle>
  <obstacle X="-5" Y="1630">Border</obstacle>
  <obstacle X="-8" Y="1701">Border</obstacle>
  <obstacle X="-6" Y="1771">Border</obstacle>
  <obstacle X="-6" Y="1841">Border</obstacle>
  <obstacle X="-4" Y="1911">Border</obstacle>
  <obstacle X="77" Y="1926">Border</obstacle>
  <obstacle X="154" Y="1923">Border</obstacle>
  <obstacle X="236" Y="1925">Border</obstacle>
  <obstacle X="320" Y="1925">Border</obstacle>
  <obstacle X="403" Y="1924">Border</obstacle>
  <obstacle X="484" Y="1926">Border</obstacle>
  <obstacle X="553" Y="1925">Border</obstacle>
  <obstacle X="619" Y="1926">Border</obstacle>
  <obstacle X="206" Y="143">Tree</obstacle>
  <obstacle X="206" Y="209">Tree</obstacle>
  <obstacle X="204" Y="275">Tree</obstacle>
  <obstacle X="205" Y="342">Tree</obstacle>
  <obstacle X="430" Y="304">Tree</obstacle>
  <obstacle X="641" Y="160">Tree</obstacle>
  <obstacle X="643" Y="283">Tree</obstacle>
  <obstacle X="207" Y="407">Tree</obstacle>
  <obstacle X="209" Y="474">Tree</obstacle>
  <obstacle X="209" Y="542">Tree</obstacle>
  <obstacle X="278" Y="543">Tree</obstacle>
  <obstacle X="355" Y="541">Tree</obstacle>
  <obstacle X="431" Y="542">Tree</obstacle>
  <obstacle X="644" Y="350">Tree</obstacle>
  <obstacle X="644" Y="414">Tree</obstacle>
  <obstacle X="641" Y="481">Tree</obstacle>
  <obstacle X="429" Y="607">Tree</obstacle>
  <obstacle X="641" Y="541">Tree</obstacle>
  <obstacle X="642" Y="221">Tree</obstacle>
  <obstacle X="423" Y="64">Tree</obstacle>
  <obstacle X="639" Y="65">Bush</obstacle>
  <obstacle X="640" Y="104">Bush</obstacle>
  <obstacle X="496" Y="542">Bush</obstacle>
  <obstacle X="571" Y="544">Bush</obstacle>
  <obstacle X="430" Y="671">Tree</obstacle>
  <obstacle X="639" Y="605">Tree</obstacle>
  <obstacle X="638" Y="666">Tree</obstacle>
  <obstacle X="430" Y="735">Tree</obstacle>
  <obstacle X="355" Y="738">Tree</obstacle>
  <obstacle X="129" Y="735">Tree</obstacle>
  <obstacle X="202" Y="740">Tree</obstacle>
  <obstacle X="276" Y="740">Tree</obstacle>
  <obstacle X="55" Y="736">Tree</obstacle>
  <obstacle X="351" Y="656">Fountain</obstacle>
  <obstacle X="637" Y="731">Tree</obstacle>
  <obstacle X="636" Y="795">Tree</obstacle>
  <obstacle X="637" Y="861">Tree</obstacle>
  <obstacle X="253" Y="798">Tree</obstacle>
  <obstacle X="252" Y="862">Tree</obstacle>
  <obstacle X="252" Y="925">Tree</obstacle>
  <obstacle X="178" Y="925">Tree</obstacle>
  <obstacle X="726" Y="862">Pond</obstacle>
  <obstacle X="1002" Y="856">Tree</obstacle>
  <obstacle X="431" Y="926">Tree</obstacle>
  <obstacle X="433" Y="800">Tree</obstacle>
  <obstacle X="639" Y="930">Tree</obstacle>
  <obstacle X="432" Y="860">Tree</obstacle>
  <obstacle X="339" Y="933">Bush</obstacle>
  <obstacle X="430" Y="987">Tree</obstacle>
  <obstacle X="432" Y="1053">Tree</obstacle>
  <obstacle X="431" Y="1113">Tree</obstacle>
  <obstacle X="180" Y="1238">Tree</obstacle>
  <obstacle X="178" Y="1112">Tree</obstacle>
  <obstacle X="175" Y="986">Tree</obstacle>
  <obstacle X="171" Y="1051">Tree</obstacle>
  <obstacle X="180" Y="1176">Tree</obstacle>
  <obstacle X="176" Y="1303">Tree</obstacle>
  <obstacle X="427" Y="1178">Tree</obstacle>
  <obstacle X="178" Y="1369">Tree</obstacle>
  <obstacle X="175" Y="1433">Tree</obstacle>
  <obstacle X="178" Y="1494">Tree</obstacle>
  <obstacle X="181" Y="1553">Tree</obstacle>
  <obstacle X="181" Y="1618">Tree</obstacle>
  <obstacle X="253" Y="1617">Tree</obstacle>
  <obstacle X="331" Y="1614">Tree</obstacle>
  <obstacle X="401" Y="1612">Tree</obstacle>
  <obstacle X="476" Y="1610">Tree</obstacle>
  <obstacle X="553" Y="1609">Tree</obstacle>
  <obstacle X="1002" Y="921">Tree</obstacle>
  <obstacle X="431" Y="1242">Tree</obstacle>
  <obstacle X="433" Y="1309">Tree</obstacle>
  <obstacle X="435" Y="1374">Tree</obstacle>
  <obstacle X="646" Y="1174">Tree</obstacle>
  <obstacle X="715" Y="154">Tree</obstacle>
  <obstacle X="794" Y="153">Tree</obstacle>
  <obstacle X="866" Y="153">Tree</obstacle>
  <obstacle X="940" Y="151">Tree</obstacle>
  <obstacle X="1015" Y="150">Tree</obstacle>
  <obstacle X="712" Y="344">Tree</obstacle>
  <obstacle X="786" Y="343">Tree</obstacle>
  <obstacle X="863" Y="345">Tree</obstacle>
  <obstacle X="936" Y="344">Tree</obstacle>
  <obstacle X="1013" Y="345">Tree</obstacle>
  <obstacle X="1089" Y="148">Tree</obstacle>
  <obstacle X="1154" Y="149">Tree</obstacle>
  <obstacle X="1225" Y="152">Tree</obstacle>
  <obstacle X="1300" Y="154">Tree</obstacle>
  <obstacle X="1373" Y="152">Tree</obstacle>
  <obstacle X="1601" Y="150">Tree</obstacle>
  <obstacle X="1674" Y="151">Tree</obstacle>
  <obstacle X="1690" Y="208">Tree</obstacle>
  <obstacle X="1691" Y="270">Tree</obstacle>
  <obstacle X="1692" Y="333">Tree</obstacle>
  <obstacle X="1015" Y="408">Tree</obstacle>
  <obstacle X="1205" Y="208">Tree</obstacle>
  <obstacle X="1201" Y="271">Tree</obstacle>
  <obstacle X="1204" Y="333">Tree</obstacle>
  <obstacle X="1205" Y="397">Tree</obstacle>
  <obstacle X="1202" Y="463">Tree</obstacle>
  <obstacle X="1013" Y="470">Tree</obstacle>
  <obstacle X="1010" Y="531">Tree</obstacle>
  <obstacle X="1009" Y="595">Tree</obstacle>
  <obstacle X="1007" Y="659">Tree</obstacle>
  <obstacle X="1007" Y="727">Tree</obstacle>
  <obstacle X="1009" Y="792">Tree</obstacle>
  <obstacle X="201" Y="55">Bush</obstacle>
  <obstacle X="202" Y="99">Bush</obstacle>
  <obstacle X="75" Y="1769">Tree</obstacle>
  <obstacle X="155" Y="1766">Tree</obstacle>
  <obstacle X="232" Y="1767">Tree</obstacle>
  <obstacle X="302" Y="1766">Tree</obstacle>
  <obstacle X="378" Y="1764">Tree</obstacle>
  <obstacle X="451" Y="1763">Tree</obstacle>
  <obstacle X="527" Y="1763">Tree</obstacle>
  <obstacle X="602" Y="1764">Tree</obstacle>
  <obstacle X="681" Y="1764">Tree</obstacle>
  <obstacle X="979" Y="1757">Tree</obstacle>
  <obstacle X="1195" Y="1754">Tree</obstacle>
  <obstacle X="895" Y="1760">Tree</obstacle>
  <obstacle X="762" Y="1755">Pond</obstacle>
  <obstacle X="1062" Y="1747">Pond</obstacle>
  <obstacle X="1351" Y="1744">Pond</obstacle>
  <obstacle X="1277" Y="1753">Tree</obstacle>
  <obstacle X="1481" Y="1751">Tree</obstacle>
  <obstacle X="1563" Y="1748">Tree</obstacle>
  <obstacle X="1643" Y="1751">Tree</obstacle>
  <obstacle X="1720" Y="1751">Tree</obstacle>
  <obstacle X="1693" Y="395">Tree</obstacle>
  <obstacle X="1691" Y="463">Tree</obstacle>
  <obstacle X="1692" Y="527">Tree</obstacle>
  <obstacle X="1692" Y="594">Tree</obstacle>
  <obstacle X="1694" Y="654">Tree</obstacle>
  <obstacle X="1692" Y="718">Tree</obstacle>
  <obstacle X="1692" Y="780">Tree</obstacle>
  <obstacle X="1522" Y="852">Tree</obstacle>
  <obstacle X="1695" Y="898">Tree</obstacle>
  <obstacle X="1698" Y="967">Tree</obstacle>
  <obstacle X="1702" Y="1033">Tree</obstacle>
  <obstacle X="1708" Y="1103">Tree</obstacle>
  <obstacle X="1721" Y="1684">Tree</obstacle>
  <obstacle X="1719" Y="1619">Tree</obstacle>
  <obstacle X="1719" Y="1556">Tree</obstacle>
  <obstacle X="1718" Y="1489">Tree</obstacle>
  <obstacle X="1716" Y="1424">Tree</obstacle>
  <obstacle X="1715" Y="1356">Tree</obstacle>
  <obstacle X="1711" Y="1293">Tree</obstacle>
  <obstacle X="1712" Y="1227">Tree</obstacle>
  <obstacle X="1708" Y="1169">Tree</obstacle>
  <obstacle X="1207" Y="526">Tree</obstacle>
  <obstacle X="1209" Y="593">Tree</obstacle>
  <obstacle X="1212" Y="659">Tree</obstacle>
  <obstacle X="1208" Y="723">Tree</obstacle>
  <obstacle X="1208" Y="787">Tree</obstacle>
  <obstacle X="861" Y="863">Bush</obstacle>
  <obstacle X="915" Y="863">Bush</obstacle>
  <obstacle X="1444" Y="153">Bush</obstacle>
  <obstacle X="1522" Y="155">Bush</obstacle>
  <obstacle X="646" Y="1109">Tree</obstacle>
  <obstacle X="725" Y="1109">Tree</obstacle>
  <obstacle X="801" Y="1108">Tree</obstacle>
  <obstacle X="870" Y="1108">Tree</obstacle>
  <obstacle X="1206" Y="853">Tree</obstacle>
  <obstacle X="1205" Y="918">Tree</obstacle>
  <obstacle X="1205" Y="984">Tree</obstacle>
  <obstacle X="1202" Y="1050">Tree</obstacle>
  <obstacle X="949" Y="1108">Tree</obstacle>
  <obstacle X="1025" Y="1109">Tree</obstacle>
  <obstacle X="1100" Y="1110">Tree</obstacle>
  <obstacle X="1171" Y="1108">Tree</obstacle>
  <obstacle X="1273" Y="393">Tree</obstacle>
  <obstacle X="1354" Y="393">Tree</obstacle>
  <obstacle X="1431" Y="394">Tree</obstacle>
  <obstacle X="1509" Y="392">Tree</obstacle>
  <obstacle X="1612" Y="590">Tree</obstacle>
  <obstacle X="1530" Y="587">Tree</obstacle>
  <obstacle X="1454" Y="586">Tree</obstacle>
  <obstacle X="1378" Y="588">Tree</obstacle>
  <obstacle X="1283" Y="785">Tree</obstacle>
  <obstacle X="1365" Y="786">Tree</obstacle>
  <obstacle X="1446" Y="788">Tree</obstacle>
  <obstacle X="1525" Y="786">Tree</obstacle>
  <obstacle X="1691" Y="843">Tree</obstacle>
  <obstacle X="1520" Y="916">Tree</obstacle>
  <obstacle X="1523" Y="985">Tree</obstacle>
  <obstacle X="1562" Y="393">Bush</obstacle>
  <obstacle X="1625" Y="392">Bush</obstacle>
  <obstacle X="1291" Y="593">Bush</obstacle>
  <obstacle X="1602" Y="779">Bush</obstacle>
  <obstacle X="1519" Y="1052">Tree</obstacle>
  <obstacle X="1437" Y="1054">Tree</obstacle>
  <obstacle X="1355" Y="1052">Tree</obstacle>
  <obstacle X="1279" Y="1055">Bush</obstacle>
  <obstacle X="1337" Y="881">Fountain</obstacle>
  <obstacle X="691" Y="1704">Tree</obstacle>
  <obstacle X="887" Y="1694">Tree</obstacle>
  <obstacle X="725" Y="1641">Tree</obstacle>
  <obstacle X="794" Y="1615">Tree</obstacle>
  <obstacle X="863" Y="1631">Tree</obstacle>
  <obstacle X="994" Y="1695">Tree</obstacle>
  <obstacle X="1024" Y="1627">Tree</obstacle>
  <obstacle X="1097" Y="1614">Tree</obstacle>
  <obstacle X="1170" Y="1638">Tree</obstacle>
  <obstacle X="1194" Y="1698">Tree</obstacle>
  <obstacle X="1276" Y="1694">Tree</obstacle>
  <obstacle X="1303" Y="1631">Tree</obstacle>
  <obstacle X="1381" Y="1604">Tree</obstacle>
  <obstacle X="1453" Y="1618">Tree</obstacle>
  <obstacle X="1483" Y="1686">Tree</obstacle>
  <obstacle X="645" Y="1233">Tree</obstacle>
  <obstacle X="647" Y="1365">Tree</obstacle>
  <obstacle X="677" Y="1421">Tree</obstacle>
  <obstacle X="705" Y="1477">Tree</obstacle>
  <obstacle X="724" Y="1521">Tree</obstacle>
  <obstacle X="732" Y="1574">Tree</obstacle>
  <obstacle X="645" Y="1294">Tree</obstacle>
  <obstacle X="254" Y="1221">Bush</obstacle>
  <obstacle X="348" Y="1220">Bush</obstacle>
  <obstacle X="838" Y="1209">Bush</obstacle>
  <obstacle X="832" Y="1267">Bush</obstacle>
  <obstacle X="830" Y="1320">Bush</obstacle>
  <obstacle X="826" Y="1374">Bush</obstacle>
  <obstacle X="822" Y="1434">Bush</obstacle>
  <obstacle X="820" Y="1488">Bush</obstacle>
  <obstacle X="899" Y="1490">Bush</obstacle>
  <obstacle X="979" Y="1493">Bush</obstacle>
  <obstacle X="1090" Y="1206">Bush</obstacle>
  <obstacle X="1095" Y="1261">Bush</obstacle>
  <obstacle X="1093" Y="1319">Bush</obstacle>
  <obstacle X="1096" Y="1382">Bush</obstacle>
  <obstacle X="1093" Y="1436">Bush</obstacle>
  <obstacle X="1098" Y="1487">Bush</obstacle>
  <obstacle X="1578" Y="1202">Bush</obstacle>
  <obstacle X="1496" Y="1203">Bush</obstacle>
  <obstacle X="1416" Y="1206">Bush</obstacle>
  <obstacle X="1407" Y="1258">Bush</obstacle>
  <obstacle X="1408" Y="1310">Bush</obstacle>
  <obstacle X="1409" Y="1363">Bush</obstacle>
  <obstacle X="1414" Y="1418">Bush</obstacle>
  <obstacle X="1415" Y="1476">Bush</obstacle>
  <obstacle X="1492" Y="1479">Bush</obstacle>
  <obstacle X="1568" Y="1475">Bush</obstacle>
  <obstacle X="1490" Y="1340">Bush</obstacle>
  <obstacle X="1289" Y="1350">Fountain</obstacle>
  <item X="204" Y="850">Coin</item>
  <item X="112" Y="851">Apple</item>
  <item X="378" Y="858">Coin</item>
  <item X="762" Y="272">Coin</item>
  <item X="103" Y="696">Apple</item>
  <item X="166" Y="1876">Coin</item>
  <item X="1851" Y="1871">CandyBar</item>
  <item X="107" Y="1885">CandyBar</item>
  <item X="980" Y="436">WaterBottle</item>
  <item X="745" Y="434">Apple</item>
  <item X="1461" Y="898">Apple</item>
  <item X="1461" Y="990">Coin</item>
  <item X="1293" Y="1439">Apple</item>
  <item X="1660" Y="1699">Coin</item>
  <item X="769" Y="1214">Coin</item>
  <npc X="549" Y="311">PoliceB</npc>
  <npc X="1462" Y="279">PoliceB</npc>
  <npc X="1473" Y="700">PoliceB</npc>
  <npc X="789" Y="1709">PoliceB</npc>
  <npc X="1087" Y="1702">PoliceB</npc>
  <npc X="1425" Y="1693">PoliceB</npc>
  <npc X="368" Y="1095">PoliceB</npc>
  <npc X="1376" Y="1693">PoliceB</npc>
  <npc X="1130" Y="1700">PoliceB</npc>
  <npc X="830" Y="1709">PoliceB</npc>
  <npc X="846" Y="669">PoliceB</npc>
</world>